odoo/addons/l10n_th_vendor_tax_invoice/README.rst
odoo/addons/l10n_th_vendor_tax_invoice/__init__.py
odoo/addons/l10n_th_vendor_tax_invoice/__manifest__.py
odoo/addons/l10n_th_vendor_tax_invoice/i18n/l10n_th_vendor_tax_invoice.pot
odoo/addons/l10n_th_vendor_tax_invoice/models/__init__.py
odoo/addons/l10n_th_vendor_tax_invoice/models/account.py
odoo/addons/l10n_th_vendor_tax_invoice/models/account_invoice.py
odoo/addons/l10n_th_vendor_tax_invoice/models/account_move.py
odoo/addons/l10n_th_vendor_tax_invoice/models/account_payment.py
odoo/addons/l10n_th_vendor_tax_invoice/models/product.py
odoo/addons/l10n_th_vendor_tax_invoice/readme/CONTRIBUTORS.rst
odoo/addons/l10n_th_vendor_tax_invoice/readme/DESCRIPTION.rst
odoo/addons/l10n_th_vendor_tax_invoice/readme/HISTORY.rst
odoo/addons/l10n_th_vendor_tax_invoice/readme/INSTALL.rst
odoo/addons/l10n_th_vendor_tax_invoice/readme/USAGE.rst
odoo/addons/l10n_th_vendor_tax_invoice/security/ir.model.access.csv
odoo/addons/l10n_th_vendor_tax_invoice/static/description/icon.png
odoo/addons/l10n_th_vendor_tax_invoice/static/description/index.html
odoo/addons/l10n_th_vendor_tax_invoice/tests/__init__.py
odoo/addons/l10n_th_vendor_tax_invoice/tests/test_vendor_tax_invoice.py
odoo/addons/l10n_th_vendor_tax_invoice/views/account_invoice.xml
odoo/addons/l10n_th_vendor_tax_invoice/views/account_payment_view.xml
odoo/addons/l10n_th_vendor_tax_invoice/views/account_view.xml
odoo/addons/l10n_th_vendor_tax_invoice/wizard/__init__.py
odoo/addons/l10n_th_vendor_tax_invoice/wizard/wizard_tax_adjustments.py
odoo/addons/l10n_th_vendor_tax_invoice/wizard/wizard_tax_adjustments_view.xml
odoo12_addon_l10n_th_vendor_tax_invoice-12.0.2.2.0.dist-info/METADATA
odoo12_addon_l10n_th_vendor_tax_invoice-12.0.2.2.0.dist-info/WHEEL
odoo12_addon_l10n_th_vendor_tax_invoice-12.0.2.2.0.dist-info/top_level.txt
odoo12_addon_l10n_th_vendor_tax_invoice-12.0.2.2.0.dist-info/RECORD
