Metadata-Version: 2.1
Name: odoo12-addon-l10n-th-vendor-tax-invoice
Version: 12.0.2.2.0
Summary: Thai Localization - Account Vendor Tax Invoice
Home-page: https://github.com/OCA/l10n-thailand/
Author: Ecosoft,Odoo Community Association (OCA)
Author-email: support@odoo-community.org
License: AGPL-3
Platform: UNKNOWN
Classifier: Programming Language :: Python
Classifier: Framework :: Odoo
Classifier: License :: OSI Approved :: GNU Affero General Public License v3
Classifier: Development Status :: 3 - Alpha
Requires-Python: >=3.5
Requires-Dist: odoo12-addon-account-create-tax-cash-basis-entry-hook
Requires-Dist: odoo (<12.1dev,>=12.0a)
